sipher/__init__.py
sipher/__main__.py
sipher/_base64.py
sipher/_morse.py
sipher/_rsa.py
sipher/_sipher.py
sipher/sipherutil.py
sipher-1.0.3.dist-info/LICENSE
sipher-1.0.3.dist-info/METADATA
sipher-1.0.3.dist-info/WHEEL
sipher-1.0.3.dist-info/entry_points.txt
sipher-1.0.3.dist-info/top_level.txt
sipher-1.0.3.dist-info/RECORD
