Metadata-Version: 2.1
Name: sipher
Version: 1.0.3
Summary: To encrypt and decrypt message.
Author-email: srg <srg.code@pm.me>
License: Apache License, Version 2.0
Project-URL: Homepage, https://github.com/codesrg/sipher
Project-URL: Bug Tracker, https://github.com/codesrg/sipher/issues
Keywords: sipher,cipher,morse,base64,rsa,encrypt,decrypt
Classifier: Programming Language :: Python :: 3
Classifier: License :: OSI Approved :: Apache Software License
Classifier: Operating System :: OS Independent
Requires-Python: >=3.6
License-File: LICENSE
Requires-Dist: srutil
Requires-Dist: rsa
